workplace_extractor/Counter.py
workplace_extractor/Extractor.py
workplace_extractor/Extractors/CommentExtractor.py
workplace_extractor/Extractors/EventExtractor.py
workplace_extractor/Extractors/GroupExtractor.py
workplace_extractor/Extractors/InteractionExtractor.py
workplace_extractor/Extractors/PersonExtractor.py
workplace_extractor/Extractors/PollExtractor.py
workplace_extractor/Extractors/PostExtractor.py
workplace_extractor/Extractors/__init__.py
workplace_extractor/Nodes/Author.py
workplace_extractor/Nodes/Event.py
workplace_extractor/Nodes/Group.py
workplace_extractor/Nodes/Interaction.py
workplace_extractor/Nodes/Node.py
workplace_extractor/Nodes/NodeCollection.py
workplace_extractor/Nodes/Poll.py
workplace_extractor/Nodes/Post.py
workplace_extractor/Nodes/__init__.py
workplace_extractor/__init__.py
workplace_extractor-0.9.9.dist-info/LICENSE.txt
workplace_extractor-0.9.9.dist-info/METADATA
workplace_extractor-0.9.9.dist-info/WHEEL
workplace_extractor-0.9.9.dist-info/RECORD
