Metadata-Version: 2.1
Name: workplace_extractor
Version: 0.9.9
Summary: Extract data created in a corporate Workplace by Facebook installation using the Graph/SCIM APIs
Home-page: https://github.com/denisduarte/workplace_extractor
License: MIT
Keywords: extractor,workplace
Author: Denis Duarte
Author-email: den.duarte@gmail.com
Classifier: Development Status :: 4 - Beta
Classifier: Intended Audience :: Developers
Classifier: License :: OSI Approved :: MIT License
Classifier: Programming Language :: Python :: 2
Classifier: Programming Language :: Python :: 2.7
Classifier: Programming Language :: Python :: 3
Classifier: Programming Language :: Python :: 3.4
Classifier: Programming Language :: Python :: 3.5
Classifier: Programming Language :: Python :: 3.6
Classifier: Programming Language :: Python :: 3.7
Classifier: Programming Language :: Python :: 3.8
Classifier: Programming Language :: Python :: 3.9
Classifier: Programming Language :: Python :: 3.10
Classifier: Programming Language :: Python :: 3.11
Classifier: Programming Language :: Python :: 3.12
Classifier: Topic :: Software Development :: Build Tools
Requires-Dist: aiohttp (>=3.7,<4.0)
Requires-Dist: asyncio (>=3.4,<4.0)
Requires-Dist: matplotlib (>=3.4.2,<4.0.0)
Requires-Dist: networkx (>=2.5.1,<3.0.0)
Requires-Dist: numpy (>=1.20,<2.0)
Requires-Dist: pandas (>=1.2,<2.0)
Requires-Dist: scipy (>=1.8.0,<2.0.0)
Project-URL: Repository, https://github.com/denisduarte/workplace_extractor
